flint/__init__.py
flint/app.py
flint/config.py
flint/custom_markdown.py
flint/styles.tcss
flint/styles/academic.tcss
flint/styles/ascii.tcss
flint/styles/blueprint.tcss
flint/styles/cyberpunk.tcss
flint/styles/minimal.tcss
flint/styles/obsidian.tcss
flint/styles/retro.tcss
flint_markdown_viewer-0.1.2.dist-info/licenses/LICENSE
flint_markdown_viewer-0.1.2.dist-info/METADATA
flint_markdown_viewer-0.1.2.dist-info/WHEEL
flint_markdown_viewer-0.1.2.dist-info/entry_points.txt
flint_markdown_viewer-0.1.2.dist-info/top_level.txt
flint_markdown_viewer-0.1.2.dist-info/RECORD
