Metadata-Version: 2.4
Name: flint-markdown-viewer
Version: 0.1.2
Summary: Flint: A premium terminal-based Markdown viewer with interactive tables, high-res images, and Obsidian-style callouts.
Author: Pratik Munot <munotpratik2009@gmail.com>
License: MIT License
Project-URL: Homepage, https://github.com/pratik-m/flint
Project-URL: Repository, https://github.com/pratik-m/flint
Project-URL: Issues, https://github.com/pratik-m/flint/issues
Keywords: markdown,tui,textual,viewer,mermaid,obsidian,flint
Classifier: Programming Language :: Python :: 3
Classifier: License :: OSI Approved :: MIT License
Classifier: Operating System :: OS Independent
Classifier: Environment :: Console
Classifier: Topic :: Text Processing :: Markup :: Markdown
Requires-Python: >=3.12
License-File: LICENSE
Requires-Dist: mermaid-py>=0.8.1
Requires-Dist: pillow>=10.4.0
Requires-Dist: platformdirs>=4.0.0
Requires-Dist: requests>=2.31.0
Requires-Dist: term-image>=0.7.2
Requires-Dist: textual>=0.86.0
Requires-Dist: textual-image[textual]>=0.8.4
Dynamic: license-file
